<?xml version="1.0"?>

<metadata
    xmlns="http://example.org/myapp/"
    xmlns:xsi="http://www.w3.org/2001/XMLSchema-instance"
    xsi:schemaLocation="http://purl.org/dc/elements/1.1/"
    xmlns:dc="http://purl.org/dc/elements/1.1/"
    xmlns:dcterms="http://purl.org/dc/terms/">

	<dc:identifier>Princess Cichlid</dc:identifier>
	<dc:title>Neolamprologus brichardi</dc:title>
	<dc:type>Territorial and aggressive to other species</dc:type>
	<dcterms:created>Easy</dcterms:created>
	<dcterms:extent>4 inches</dcterms:extent>
	<dcterms:medium>PH 8.0 - 9.0 but will do fine in lower PH down to a low 7, Temp 70 - 80 F</dcterms:medium>
	<dcterms:provenance>Middle-Bottom</dcterms:provenance>
	<dcterms:requires>Ominvore</dcterms:requires>
	<dcterms:spatial>Lake Tanganyika</dcterms:spatial>
</metadata>
